bias_fairness_auditor/__init__.py
bias_fairness_auditor/auditor.py
bias_fairness_auditor/types.py
bias_fairness_auditor-0.1.0.dist-info/licenses/LICENSE
bias_fairness_auditor-0.1.0.dist-info/METADATA
bias_fairness_auditor-0.1.0.dist-info/WHEEL
bias_fairness_auditor-0.1.0.dist-info/top_level.txt
bias_fairness_auditor-0.1.0.dist-info/RECORD
