Metadata-Version: 2.4
Name: bias-fairness-auditor
Version: 0.1.0
Summary: Production-ready ML fairness auditing with bias detection and mitigation
Author-email: Pranay M <pranay@example.com>
License: MIT
Project-URL: Homepage, https://github.com/pranaym/bias-fairness-auditor
Project-URL: Documentation, https://github.com/pranaym/bias-fairness-auditor#readme
Project-URL: Repository, https://github.com/pranaym/bias-fairness-auditor
Keywords: fairness,bias,ml,audit,ethics,responsible-ai
Classifier: Development Status :: 4 - Beta
Classifier: Intended Audience :: Developers
Classifier: License :: OSI Approved :: MIT License
Classifier: Programming Language :: Python :: 3
Classifier: Programming Language :: Python :: 3.8
Classifier: Programming Language :: Python :: 3.9
Classifier: Programming Language :: Python :: 3.10
Classifier: Programming Language :: Python :: 3.11
Classifier: Programming Language :: Python :: 3.12
Classifier: Topic :: Scientific/Engineering :: Artificial Intelligence
Requires-Python: >=3.8
License-File: LICENSE
Provides-Extra: ml
Requires-Dist: numpy>=1.20.0; extra == "ml"
Requires-Dist: pandas>=1.3.0; extra == "ml"
Requires-Dist: scikit-learn>=1.0.0; extra == "ml"
Provides-Extra: full
Requires-Dist: numpy>=1.20.0; extra == "full"
Requires-Dist: pandas>=1.3.0; extra == "full"
Requires-Dist: scikit-learn>=1.0.0; extra == "full"
Requires-Dist: aif360>=0.5.0; extra == "full"
Provides-Extra: dev
Requires-Dist: pytest>=7.0.0; extra == "dev"
Requires-Dist: pytest-asyncio>=0.21.0; extra == "dev"
Requires-Dist: black>=23.0.0; extra == "dev"
Requires-Dist: mypy>=1.0.0; extra == "dev"
Dynamic: license-file
